minisound/__init__.py
minisound/base.py
minisound/bell.py
minisound/proc.py
minisound/wrap.py
minisound/libs/__init__.py
minisound/libs/argparse.py
minisound/libs/os.py
minisound/libs/logging/__init__.py
minisound/libs/logging/config.py
minisound/libs/logging/handlers.py
minisound/libs/requests/__init__.py
minisound/libs/requests/__version__.py
minisound/libs/requests/_internal_utils.py
minisound/libs/requests/compat.py
minisound/libs/requests/cookies.py
minisound/libs/requests/exceptions.py
minisound/libs/requests/help.py
minisound/libs/requests/hooks.py
minisound/libs/requests/models.py
minisound/libs/requests/packages.py
minisound/libs/requests/sessions.py
minisound/libs/requests/status_codes.py
minisound/libs/requests/structures.py
minisound/libs/requests/utils.py
minisound-0.0.1.dist-info/LICENSE
minisound-0.0.1.dist-info/METADATA
minisound-0.0.1.dist-info/WHEEL
minisound-0.0.1.dist-info/top_level.txt
minisound-0.0.1.dist-info/RECORD
