Metadata-Version: 2.1
Name: minisound
Version: 0.0.1
Summary: 🔊 Play music and sounds in your Python scripts
Author: Derek Moody
License: LGPL-3.0
Requires-Python: >=3.6
License-File: LICENSE
Requires-Dist: anyio
Requires-Dist: boombox
Requires-Dist: idna
Requires-Dist: playsound
Requires-Dist: sniffio
